ssplot/CommandLine.py
ssplot/FigureSize.py
ssplot/GridStyle.py
ssplot/LatencyCdf.py
ssplot/LatencyPdf.py
ssplot/LatencyPercentile.py
ssplot/LatencyPlot.py
ssplot/LoadAverageHops.py
ssplot/LoadHopsStats.py
ssplot/LoadLatency.py
ssplot/LoadLatencyCompare.py
ssplot/LoadLatencyStats.py
ssplot/LoadPercentMinimal.py
ssplot/LoadRate.py
ssplot/LoadRatePercent.py
ssplot/LoadRateStats.py
ssplot/MultibarPlot.py
ssplot/MultilinePlot.py
ssplot/PlotBarStyle.py
ssplot/PlotLineStyle.py
ssplot/SampleStats.py
ssplot/SimTimeCompare.py
ssplot/TimeAverageHops.py
ssplot/TimeLatency.py
ssplot/TimeLatencyScatter.py
ssplot/TimePercentMinimal.py
ssplot/__init__.py
ssplot/consts.py
ssplot/utils.py
ssplot-1.2.5.data/scripts/ssplot
ssplot-1.2.5.dist-info/LICENSE
ssplot-1.2.5.dist-info/METADATA
ssplot-1.2.5.dist-info/NOTICE
ssplot-1.2.5.dist-info/WHEEL
ssplot-1.2.5.dist-info/top_level.txt
ssplot-1.2.5.dist-info/RECORD
