Metadata-Version: 2.1
Name: ssplot
Version: 1.2.5
Summary: ssplot aggregate stats file Python wrapper
Home-page: http://github.com/nicmcd/ssplot
Author: Nic McDonald
Author-email: nicci02@hotmail.com
License: BSD 3 Clause
License-File: LICENSE
License-File: NOTICE
Requires-Dist: percentile (>=1.0.3)
Requires-Dist: handycsv (>=4.0.0)
Requires-Dist: matplotlib (>=3.3.4)
Requires-Dist: numpy (>=1.20.1)
